kaomojin/__init__.py
kaomojin/dumpers.py
kaomojin/kaomojin.py
kaomojin/data/__init__.py
kaomojin/data/kaomoji/all.tsv
kaomojin-20.6.0a0.dist-info/LICENSE.txt
kaomojin-20.6.0a0.dist-info/METADATA
kaomojin-20.6.0a0.dist-info/WHEEL
kaomojin-20.6.0a0.dist-info/entry_points.txt
kaomojin-20.6.0a0.dist-info/top_level.txt
kaomojin-20.6.0a0.dist-info/RECORD
